odoo/addons/shopinvader_api_signin_jwt/README.rst
odoo/addons/shopinvader_api_signin_jwt/__init__.py
odoo/addons/shopinvader_api_signin_jwt/__manifest__.py
odoo/addons/shopinvader_api_signin_jwt/i18n/shopinvader_api_signin_jwt.pot
odoo/addons/shopinvader_api_signin_jwt/readme/CONTRIBUTORS.rst
odoo/addons/shopinvader_api_signin_jwt/readme/DESCRIPTION.rst
odoo/addons/shopinvader_api_signin_jwt/readme/INSTALL.rst
odoo/addons/shopinvader_api_signin_jwt/readme/ROADMAP.rst
odoo/addons/shopinvader_api_signin_jwt/routers/__init__.py
odoo/addons/shopinvader_api_signin_jwt/routers/signin.py
odoo/addons/shopinvader_api_signin_jwt/security/acl_res_partner.xml
odoo/addons/shopinvader_api_signin_jwt/security/res_groups.xml
odoo/addons/shopinvader_api_signin_jwt/static/description/index.html
odoo/addons/shopinvader_api_signin_jwt/tests/__init__.py
odoo/addons/shopinvader_api_signin_jwt/tests/test_signin.py
odoo_addon_shopinvader_api_signin_jwt-16.0.1.1.2.dist-info/METADATA
odoo_addon_shopinvader_api_signin_jwt-16.0.1.1.2.dist-info/WHEEL
odoo_addon_shopinvader_api_signin_jwt-16.0.1.1.2.dist-info/top_level.txt
odoo_addon_shopinvader_api_signin_jwt-16.0.1.1.2.dist-info/RECORD
