Metadata-Version: 2.1
Name: odoo-addon-shopinvader_api_signin_jwt
Version: 16.0.1.1.2
Summary: This module adds a signin service with jwt token.
Home-page: https://github.com/shopinvader/odoo-shopinvader
Author: ACSONE SA/NV
License: AGPL-3
Classifier: Programming Language :: Python
Classifier: Framework :: Odoo
Classifier: Framework :: Odoo :: 16.0
Classifier: License :: OSI Approved :: GNU Affero General Public License v3
Requires-Python: >=3.10
Requires-Dist: odoo-addon-fastapi-auth-jwt<16.1dev,>=16.0dev
Requires-Dist: odoo-addon-shopinvader-anonymous-partner<16.1dev,>=16.0dev
Requires-Dist: odoo<16.1dev,>=16.0a
